{"expireTime":9007200876954544000,"key":"create-remote-file-node-headers-https://cdn.shopify.com/s/files/1/0559/2439/2107/products/Circum_E_2_pjuzes_b6e298a6-bfa6-47ce-8ab7-06ba5d8d9912.jpg?v=1620314892","val":{"connection":"close","content-length":"1190812","content-type":"image/jpeg","cache-control":"public, max-age=31557600","expires":"Sat, 28 May 2022 11:50:35 GMT","last-modified":"Fri, 28 May 2021 11:50:37 GMT","x-image":"proxied_with_processing","access-control-allow-origin":"*","timing-allow-origin":"*","x-xss-protection":"1; mode=block","x-content-type-options":"nosniff","link":"<https://cdn.shopify.com/s/files/1/0559/2439/2107/products/Circum_E_2_pjuzes_b6e298a6-bfa6-47ce-8ab7-06ba5d8d9912.jpg>; rel=\"canonical\"","x-request-id":"fb695505a4937be8cbd2017ca09c3bb539d7fd410594eb11613705b9262a9d0c","strict-transport-security":"max-age=63072000; includeSubDomains; preload","x-dc":"gcp-us-central1","accept-ranges":"bytes","date":"Fri, 28 May 2021 14:52:27 GMT","server":"cache-ams21023-AMS","nel":"{\"report_to\":\"network-errors\",\"max_age\":600,\"failure_fraction\":1.0,\"success_fraction\":0.0}","report-to":"{\"group\":\"network-errors\",\"max_age\":2592000,\"endpoints\":[{\"url\":\"https://monorail-edge.shopifysvc.com/v1/reports/nel/20190325/imagery\"}]}","x-cdn":"Fastly, http1","x-served-by":"cache-lga21945-LGA, cache-ams21023-AMS","x-cache":"MISS, HIT","x-cache-hits":"0, 1","x-timer":"S1622213547.493154,VS0,VE2","vary":"Accept"}}